{
  "timestamp": "2026-07-08T05:08:38.859Z",
  "totalGroups": 155,
  "trulyLegitimate": 155,
  "dupesWithStolenNames": 0,
  "unverifiable": 0,
  "stolenCases": [],
  "legitimateSample": [
    {
      "match_id": "wc26-g-001",
      "minute_num": 66,
      "team_id": "mex",
      "event_type": "SUB",
      "cnt": 2,
      "players_by_id": "Luis Chávez | Gilberto Mora",
      "ids": "167,168",
      "espnCount": 2,
      "espnPlayers": "Luis Chávez | Gilberto Mora"
    },
    {
      "match_id": "wc26-g-001",
      "minute_num": 76,
      "team_id": "mex",
      "event_type": "SUB",
      "cnt": 2,
      "players_by_id": "Edson Álvarez | Armando González",
      "ids": "179,180",
      "espnCount": 2,
      "espnPlayers": "Edson Álvarez | Armando González"
    },
    {
      "match_id": "wc26-g-002",
      "minute_num": 64,
      "team_id": "cze",
      "event_type": "SUB",
      "cnt": 3,
      "players_by_id": "Adam Hlozek | Tomás Chorý | Michal Sadílek",
      "ids": "206,207,208",
      "espnCount": 3,
      "espnPlayers": "Adam Hlozek | Tomás Chorý | Michal Sadílek"
    },
    {
      "match_id": "wc26-g-002",
      "minute_num": 69,
      "team_id": "kor",
      "event_type": "SUB",
      "cnt": 2,
      "players_by_id": "Eom Ji-Sung | Oh Hyeon-Gyu",
      "ids": "210,211",
      "espnCount": 2,
      "espnPlayers": "Eom Ji-Sung | Oh Hyeon-Gyu"
    },
    {
      "match_id": "wc26-g-002",
      "minute_num": 84,
      "team_id": "kor",
      "event_type": "SUB",
      "cnt": 2,
      "players_by_id": "Kim Jin-Gyu | Park Jin-Seop",
      "ids": "217,218",
      "espnCount": 2,
      "espnPlayers": "Kim Jin-Gyu | Park Jin-Seop"
    },
    {
      "match_id": "wc26-g-003",
      "minute_num": 45,
      "team_id": "bih",
      "event_type": "YELLOW",
      "cnt": 2,
      "players_by_id": "Ermedin Demirovic | Jovo Lukic",
      "ids": "237,238",
      "espnCount": 2,
      "espnPlayers": "Ermedin Demirovic | Jovo Lukic"
    },
    {
      "match_id": "wc26-g-003",
      "minute_num": 61,
      "team_id": "can",
      "event_type": "SUB",
      "cnt": 3,
      "players_by_id": "Jacob Shaffelburg | Promise David | Ali Ahmed",
      "ids": "246,247,248",
      "espnCount": 3,
      "espnPlayers": "Jacob Shaffelburg | Promise David | Ali Ahmed"
    },
    {
      "match_id": "wc26-g-003",
      "minute_num": 62,
      "team_id": "bih",
      "event_type": "SUB",
      "cnt": 2,
      "players_by_id": "Samed Bazdar | Armin Gigovic",
      "ids": "249,250",
      "espnCount": 2,
      "espnPlayers": "Samed Bazdar | Armin Gigovic"
    },
    {
      "match_id": "wc26-g-003",
      "minute_num": 74,
      "team_id": "bih",
      "event_type": "SUB",
      "cnt": 2,
      "players_by_id": "Ivan Sunjic | Kerim Alajbegovic",
      "ids": "255,256",
      "espnCount": 2,
      "espnPlayers": "Ivan Sunjic | Kerim Alajbegovic"
    },
    {
      "match_id": "wc26-g-004",
      "minute_num": 60,
      "team_id": "qat",
      "event_type": "SUB",
      "cnt": 3,
      "players_by_id": "Ahmed Fathy | Karim Boudiaf | Ahmed Alaaeldin",
      "ids": "345,346,347",
      "espnCount": 3,
      "espnPlayers": "Ahmed Fathy | Karim Boudiaf | Ahmed Alaaeldin"
    },
    {
      "match_id": "wc26-g-004",
      "minute_num": 65,
      "team_id": "sui",
      "event_type": "SUB",
      "cnt": 2,
      "players_by_id": "Fabian Rieder | Johan Manzambi",
      "ids": "348,349",
      "espnCount": 2,
      "espnPlayers": "Fabian Rieder | Johan Manzambi"
    },
    {
      "match_id": "wc26-g-004",
      "minute_num": 89,
      "team_id": "sui",
      "event_type": "SUB",
      "cnt": 2,
      "players_by_id": "Ardon Jashari | Miro Muheim",
      "ids": "357,358",
      "espnCount": 2,
      "espnPlayers": "Ardon Jashari | Miro Muheim"
    },
    {
      "match_id": "wc26-g-005",
      "minute_num": 72,
      "team_id": "usa",
      "event_type": "SUB",
      "cnt": 2,
      "players_by_id": "Timothy Weah | Ricardo Pepi",
      "ids": "306,307",
      "espnCount": 2,
      "espnPlayers": "Timothy Weah | Ricardo Pepi"
    },
    {
      "match_id": "wc26-g-005",
      "minute_num": 79,
      "team_id": "par",
      "event_type": "SUB",
      "cnt": 2,
      "players_by_id": "Ramón Sosa | Gustavo Velázquez",
      "ids": "310,311",
      "espnCount": 2,
      "espnPlayers": "Ramón Sosa | Gustavo Velázquez"
    },
    {
      "match_id": "wc26-g-006",
      "minute_num": 45,
      "team_id": "bra",
      "event_type": "SUB",
      "cnt": 2,
      "players_by_id": "Danilo | Fabinho",
      "ids": "371,372",
      "espnCount": 2,
      "espnPlayers": "Danilo | Fabinho"
    },
    {
      "match_id": "wc26-g-006",
      "minute_num": 65,
      "team_id": "mar",
      "event_type": "SUB",
      "cnt": 2,
      "players_by_id": "Samir El Mourabet | Chemsdine Talbi",
      "ids": "376,377",
      "espnCount": 2,
      "espnPlayers": "Samir El Mourabet | Chemsdine Talbi"
    },
    {
      "match_id": "wc26-g-006",
      "minute_num": 80,
      "team_id": "mar",
      "event_type": "SUB",
      "cnt": 2,
      "players_by_id": "Anass Salah-Eddine | Ayoube Amaimouni",
      "ids": "384,385",
      "espnCount": 2,
      "espnPlayers": "Anass Salah-Eddine | Ayoube Amaimouni"
    },
    {
      "match_id": "wc26-g-007",
      "minute_num": 75,
      "team_id": "sco",
      "event_type": "SUB",
      "cnt": 3,
      "players_by_id": "Ryan Christie | Lyndon Dykes | Nathan Patterson",
      "ids": "416,417,418",
      "espnCount": 3,
      "espnPlayers": "Ryan Christie | Lyndon Dykes | Nathan Patterson"
    },
    {
      "match_id": "wc26-g-007",
      "minute_num": 83,
      "team_id": "sco",
      "event_type": "SUB",
      "cnt": 2,
      "players_by_id": "Findlay Curtis | Kenny McLean",
      "ids": "420,421",
      "espnCount": 2,
      "espnPlayers": "Findlay Curtis | Kenny McLean"
    },
    {
      "match_id": "wc26-g-007",
      "minute_num": 90,
      "team_id": "sco",
      "event_type": "YELLOW",
      "cnt": 2,
      "players_by_id": "Findlay Curtis | Kenny McLean",
      "ids": "423,424",
      "espnCount": 2,
      "espnPlayers": "Findlay Curtis | Kenny McLean"
    }
  ],
  "verdict": "DISJOINT"
}